[
  {
    "id": "61c51acf-f383-4060-b1d7-d197c85d14f8",
    "channel": "Maharani - Season 1",
    "date": "2025-07-24",
    "start": "09:00:00",
    "end": "09:46:00",
    "type": "episode",
    "program": "Episode 01: The Queen",
    "image": "https://picsum.photos/200/300",
    "description": "Rani Bharti takes on political challenges."
  },
  {
    "id": "eb870eae-4dba-4350-b166-516ff27da06f",
    "channel": "Maharani - Season 1",
    "date": "2025-07-24",
    "start": "09:46:00",
    "end": "09:48:00",
    "type": "ad",
    "program": "Ad: Airtel Promo",
    "image": "https://picsum.photos/200/300",
    "brand": "Airtel",
    "sector": "Telecom",
    "category": "Mobile Plans",
    "description": "Stay connected with Airtel 5G."
  },
  {
    "id": "ef774a79-601f-40ae-8635-f6b7ab4c8b9c",
    "channel": "Maharani - Season 1",
    "date": "2025-07-24",
    "start": "09:48:00",
    "end": "10:44:00",
    "type": "episode",
    "program": "Episode 01: The Queen",
    "image": "https://picsum.photos/200/300",
    "description": "Rani Bharti takes on political challenges."
  },
  {
    "id": "66c8bc7a-7b10-4e00-b445-2fc0ddc769ed",
    "channel": "Scam 1992 - Season 1",
    "date": "2025-07-24",
    "start": "10:44:00",
    "end": "10:45:00",
    "type": "ad",
    "program": "Ad: Sony Bravia Ad",
    "image": "https://picsum.photos/200/300",
    "brand": "Sony",
    "sector": "Electronics",
    "category": "Televisions",
    "description": "Experience vivid colors with Sony Bravia."
  },
  {
    "id": "2b5f5a38-38f5-42e8-a2c1-62ee387eacf7",
    "channel": "Scam 1992 - Season 1",
    "date": "2025-07-24",
    "start": "10:45:00",
    "end": "11:28:00",
    "type": "episode",
    "program": "Episode 07: Dalal Street",
    "image": "https://picsum.photos/200/300",
    "description": "Harshad's empire faces challenges."
  },
  {
    "id": "918ed748-2956-422a-be6c-f24c329e328e",
    "channel": "Maharani - Season 1",
    "date": "2025-07-24",
    "start": "11:28:00",
    "end": "11:29:00",
    "type": "ad",
    "program": "Ad: Sony Bravia Ad",
    "image": "https://picsum.photos/200/300",
    "brand": "Sony",
    "sector": "Electronics",
    "category": "Televisions",
    "description": "Experience vivid colors with Sony Bravia."
  },
  {
    "id": "3bde99e6-79ca-4a8c-adc9-2a672004b520",
    "channel": "Maharani - Season 1",
    "date": "2025-07-24",
    "start": "11:29:00",
    "end": "12:15:00",
    "type": "episode",
    "program": "Episode 07: Power Play",
    "image": "https://picsum.photos/200/300",
    "description": "Rani faces a political crisis."
  },
  {
    "id": "aa25337e-42a2-404e-ae9f-ee35a027fe61",
    "channel": "Maharani - Season 1",
    "date": "2025-07-24",
    "start": "12:15:00",
    "end": "12:17:00",
    "type": "ad",
    "program": "Ad: Sony Bravia Ad",
    "image": "https://picsum.photos/200/300",
    "brand": "Sony",
    "sector": "Electronics",
    "category": "Televisions",
    "description": "Experience vivid colors with Sony Bravia."
  },
  {
    "id": "edfb42ea-86db-4895-b7af-c662b2249833",
    "channel": "Maharani - Season 1",
    "date": "2025-07-24",
    "start": "12:17:00",
    "end": "13:01:00",
    "type": "episode",
    "program": "Episode 07: Power Play",
    "image": "https://picsum.photos/200/300",
    "description": "Rani faces a political crisis."
  },
  {
    "id": "30617712-5a56-45bb-8a29-c7f6d6e808a0",
    "channel": "Maharani - Season 1",
    "date": "2025-07-24",
    "start": "13:01:00",
    "end": "13:02:00",
    "type": "ad",
    "program": "Ad: Airtel Promo",
    "image": "https://picsum.photos/200/300",
    "brand": "Airtel",
    "sector": "Telecom",
    "category": "Mobile Plans",
    "description": "Stay connected with Airtel 5G."
  },
  {
    "id": "cb652f43-aee5-41e5-9cb6-ecb3a1381e82",
    "channel": "Scam 1992 - Season 1",
    "date": "2025-07-24",
    "start": "13:02:00",
    "end": "13:56:00",
    "type": "episode",
    "program": "Episode 01: Risk Se Ishq",
    "image": "https://picsum.photos/200/300",
    "description": "Harshad Mehta's rise in the stock market begins."
  },
  {
    "id": "12e5e2c0-65cc-448c-b6b5-ed81f9badf33",
    "channel": "Scam 1992 - Season 1",
    "date": "2025-07-24",
    "start": "13:56:00",
    "end": "13:58:00",
    "type": "ad",
    "program": "Ad: Sony Bravia Ad",
    "image": "https://picsum.photos/200/300",
    "brand": "Sony",
    "sector": "Electronics",
    "category": "Televisions",
    "description": "Experience vivid colors with Sony Bravia."
  },
  {
    "id": "10b14346-011b-4ccb-8c53-a27cbce7e914",
    "channel": "Scam 1992 - Season 1",
    "date": "2025-07-24",
    "start": "13:58:00",
    "end": "14:31:00",
    "type": "episode",
    "program": "Episode 01: Risk Se Ishq",
    "image": "https://picsum.photos/200/300",
    "description": "Harshad Mehta's rise in the stock market begins."
  },
  {
    "id": "7487286b-6220-4d38-ae03-d6cbbff1da67",
    "channel": "Maharani - Season 1",
    "date": "2025-07-24",
    "start": "14:31:00",
    "end": "14:32:00",
    "type": "ad",
    "program": "Ad: Sony Bravia Ad",
    "image": "https://picsum.photos/200/300",
    "brand": "Sony",
    "sector": "Electronics",
    "category": "Televisions",
    "description": "Experience vivid colors with Sony Bravia."
  },
  {
    "id": "9d9adc1e-c3ee-46c6-8a7b-aba8b091089e",
    "channel": "Scam 1992 - Season 1",
    "date": "2025-07-24",
    "start": "14:32:00",
    "end": "15:02:00",
    "type": "episode",
    "program": "Episode 01: Risk Se Ishq",
    "image": "https://picsum.photos/200/300",
    "description": "Harshad Mehta's rise in the stock market begins."
  },
  {
    "id": "c7e5697e-d19d-4e0c-9a08-01e17ca608a1",
    "channel": "Maharani - Season 1",
    "date": "2025-07-24",
    "start": "15:02:00",
    "end": "15:03:00",
    "type": "ad",
    "program": "Ad: Airtel Promo",
    "image": "https://picsum.photos/200/300",
    "brand": "Airtel",
    "sector": "Telecom",
    "category": "Mobile Plans",
    "description": "Stay connected with Airtel 5G."
  },
  {
    "id": "9bf606fa-5e1b-4ab7-b7ff-440bf84832af",
    "channel": "Maharani - Season 1",
    "date": "2025-07-24",
    "start": "15:03:00",
    "end": "15:45:00",
    "type": "episode",
    "program": "Episode 07: Power Play",
    "image": "https://picsum.photos/200/300",
    "description": "Rani faces a political crisis."
  },
  {
    "id": "f486ca48-daad-4061-b25a-53e2ff408990",
    "channel": "Scam 1992 - Season 1",
    "date": "2025-07-24",
    "start": "15:45:00",
    "end": "15:46:00",
    "type": "ad",
    "program": "Ad: Airtel Promo",
    "image": "https://picsum.photos/200/300",
    "brand": "Airtel",
    "sector": "Telecom",
    "category": "Mobile Plans",
    "description": "Stay connected with Airtel 5G."
  },
  {
    "id": "27fef09b-1016-462c-9a71-3e2ca63756ce",
    "channel": "Maharani - Season 1",
    "date": "2025-07-24",
    "start": "15:46:00",
    "end": "16:25:00",
    "type": "episode",
    "program": "Episode 07: Power Play",
    "image": "https://picsum.photos/200/300",
    "description": "Rani faces a political crisis."
  },
  {
    "id": "ee5622ea-8783-4178-82c3-8a6348f8e825",
    "channel": "Maharani - Season 1",
    "date": "2025-07-24",
    "start": "16:25:00",
    "end": "16:27:00",
    "type": "ad",
    "program": "Ad: Airtel Promo",
    "image": "https://picsum.photos/200/300",
    "brand": "Airtel",
    "sector": "Telecom",
    "category": "Mobile Plans",
    "description": "Stay connected with Airtel 5G."
  },
  {
    "id": "08f7d974-71a6-48fa-b291-d9286e35904f",
    "channel": "Scam 1992 - Season 1",
    "date": "2025-07-24",
    "start": "16:27:00",
    "end": "17:09:00",
    "type": "episode",
    "program": "Episode 07: Dalal Street",
    "image": "https://picsum.photos/200/300",
    "description": "Harshad's empire faces challenges."
  },
  {
    "id": "d8bd7c90-c50f-4390-8954-55bce0c70b57",
    "channel": "Maharani - Season 1",
    "date": "2025-07-24",
    "start": "17:09:00",
    "end": "17:11:00",
    "type": "ad",
    "program": "Ad: Sony Bravia Ad",
    "image": "https://picsum.photos/200/300",
    "brand": "Sony",
    "sector": "Electronics",
    "category": "Televisions",
    "description": "Experience vivid colors with Sony Bravia."
  },
  {
    "id": "9553564c-6411-4c14-9a38-b31aca035217",
    "channel": "Scam 1992 - Season 1",
    "date": "2025-07-24",
    "start": "17:11:00",
    "end": "18:00:00",
    "type": "episode",
    "program": "Episode 01: Risk Se Ishq",
    "image": "https://picsum.photos/200/300",
    "description": "Harshad Mehta's rise in the stock market begins."
  },
  {
    "id": "8ad4f54c-cf08-48fc-b718-b6625be8ca44",
    "channel": "Maharani - Season 1",
    "date": "2025-07-24",
    "start": "18:00:00",
    "end": "18:02:00",
    "type": "ad",
    "program": "Ad: Sony Bravia Ad",
    "image": "https://picsum.photos/200/300",
    "brand": "Sony",
    "sector": "Electronics",
    "category": "Televisions",
    "description": "Experience vivid colors with Sony Bravia."
  },
  {
    "id": "5b8a9f09-69b2-42db-9b43-14ca4b7c39f4",
    "channel": "Maharani - Season 1",
    "date": "2025-07-24",
    "start": "18:02:00",
    "end": "18:32:00",
    "type": "episode",
    "program": "Episode 07: Power Play",
    "image": "https://picsum.photos/200/300",
    "description": "Rani faces a political crisis."
  },
  {
    "id": "22378f64-5893-4e65-b445-9817bc959954",
    "channel": "Maharani - Season 1",
    "date": "2025-07-24",
    "start": "18:32:00",
    "end": "18:34:00",
    "type": "ad",
    "program": "Ad: Airtel Promo",
    "image": "https://picsum.photos/200/300",
    "brand": "Airtel",
    "sector": "Telecom",
    "category": "Mobile Plans",
    "description": "Stay connected with Airtel 5G."
  },
  {
    "id": "5ad8f40d-25c6-4ff1-98e2-d5adfb3f8fdc",
    "channel": "Maharani - Season 1",
    "date": "2025-07-24",
    "start": "18:34:00",
    "end": "19:32:00",
    "type": "episode",
    "program": "Episode 01: The Queen",
    "image": "https://picsum.photos/200/300",
    "description": "Rani Bharti takes on political challenges."
  },
  {
    "id": "4c32bed8-b22e-45bc-92e2-56b64891bbb4",
    "channel": "Scam 1992 - Season 1",
    "date": "2025-07-24",
    "start": "19:32:00",
    "end": "19:33:00",
    "type": "ad",
    "program": "Ad: Airtel Promo",
    "image": "https://picsum.photos/200/300",
    "brand": "Airtel",
    "sector": "Telecom",
    "category": "Mobile Plans",
    "description": "Stay connected with Airtel 5G."
  },
  {
    "id": "cdf6fb54-02c1-4182-b8cd-64488b5ef2ee",
    "channel": "Maharani - Season 1",
    "date": "2025-07-24",
    "start": "19:33:00",
    "end": "20:33:00",
    "type": "episode",
    "program": "Episode 07: Power Play",
    "image": "https://picsum.photos/200/300",
    "description": "Rani faces a political crisis."
  },
  {
    "id": "1468d230-8ab0-4dc3-ac6f-e97b6bc23a50",
    "channel": "Maharani - Season 1",
    "date": "2025-07-24",
    "start": "20:33:00",
    "end": "20:34:00",
    "type": "ad",
    "program": "Ad: Sony Bravia Ad",
    "image": "https://picsum.photos/200/300",
    "brand": "Sony",
    "sector": "Electronics",
    "category": "Televisions",
    "description": "Experience vivid colors with Sony Bravia."
  },
  {
    "id": "0e7a4e6c-9bd4-4979-8fbf-1badd8277061",
    "channel": "Maharani - Season 1",
    "date": "2025-07-24",
    "start": "20:34:00",
    "end": "21:00:00",
    "type": "episode",
    "program": "Episode 01: The Queen",
    "image": "https://picsum.photos/200/300",
    "description": "Rani Bharti takes on political challenges."
  }
]